playtest/__init__.py
playtest/action.py
playtest/constant.py
playtest/env.py
playtest/game.py
playtest/logger.py
playtest/state.py
playtest/test_action.py
playtest/test_state.py
playtest/agents/__init__.py
playtest/agents/base.py
playtest/agents/human.py
playtest/agents/keras_dqn.py
playtest/agents/trainer.py
playtest/components/__init__.py
playtest/components/card.py
playtest/components/core.py
playtest/components/counter.py
playtest/components/test_card.py
playtest/components/token.py
playtest-0.0.10.dist-info/LICENSE.txt
playtest-0.0.10.dist-info/METADATA
playtest-0.0.10.dist-info/WHEEL
playtest-0.0.10.dist-info/top_level.txt
playtest-0.0.10.dist-info/RECORD
