Metadata-Version: 2.1
Name: playtest
Version: 0.0.10
Summary: A library for rapid prototyping of boardgames.
Home-page: https://github.com/dat-boris/py-playtest
Author: Boris Lau
Author-email: boris@techie.im
License: MIT
Platform: UNKNOWN
Requires-Python: >=3.7
Requires-Dist: numpy
Requires-Dist: gym
Requires-Dist: tensorflow
Requires-Dist: keras-rl
Requires-Dist: wandb
